fasthog-0.1.7.data/data/lib/libfasthog.dylib
fasthog/__init__.py
fasthog-0.1.7.dist-info/RECORD
fasthog-0.1.7.dist-info/LICENSE
fasthog-0.1.7.dist-info/WHEEL
fasthog-0.1.7.dist-info/top_level.txt
fasthog-0.1.7.dist-info/METADATA
