Metadata-Version: 2.2
Name: fasthog
Version: 0.1.7
Summary: Reasonably fast implementation of HOG descriptor calculation
Home-page: https://github.com/flatironinstitute/fasthog
Author: Robert Blackwell
Author-email: rblackwell@flatironinstitute.org
License-File: LICENSE
Requires-Dist: numpy
Dynamic: author
Dynamic: author-email
Dynamic: description
Dynamic: description-content-type
Dynamic: home-page
Dynamic: requires-dist
Dynamic: summary
